onlinewebfonts_dl.py
onlinewebfonts_dl-0.0.1.dist-info/LICENSE
onlinewebfonts_dl-0.0.1.dist-info/METADATA
onlinewebfonts_dl-0.0.1.dist-info/WHEEL
onlinewebfonts_dl-0.0.1.dist-info/entry_points.txt
onlinewebfonts_dl-0.0.1.dist-info/top_level.txt
onlinewebfonts_dl-0.0.1.dist-info/RECORD
