Metadata-Version: 2.1
Name: onlinewebfonts-dl
Version: 0.0.1
Summary: UNKNOWN
Home-page: https://github.com/vgavro/onlinewebfonts-dl
Author: Victor Gavro
Author-email: vgavro@gmail.com
License: MIT License
Platform: UNKNOWN
Classifier: Development Status :: 3 - Alpha
Classifier: License :: OSI Approved :: MIT License
Classifier: Operating System :: OS Independent
Classifier: Programming Language :: Python
Classifier: Programming Language :: Python :: 3.6
Requires-Dist: requests
Requires-Dist: click
